audiomentations/__init__.py
audiomentations/augmentations/__init__.py
audiomentations/augmentations/add_background_noise.py
audiomentations/augmentations/add_color_noise.py
audiomentations/augmentations/add_gaussian_noise.py
audiomentations/augmentations/add_gaussian_snr.py
audiomentations/augmentations/add_short_noises.py
audiomentations/augmentations/adjust_duration.py
audiomentations/augmentations/air_absorption.py
audiomentations/augmentations/aliasing.py
audiomentations/augmentations/apply_impulse_response.py
audiomentations/augmentations/band_pass_filter.py
audiomentations/augmentations/band_stop_filter.py
audiomentations/augmentations/base_butterword_filter.py
audiomentations/augmentations/bit_crush.py
audiomentations/augmentations/clip.py
audiomentations/augmentations/clipping_distortion.py
audiomentations/augmentations/gain.py
audiomentations/augmentations/gain_transition.py
audiomentations/augmentations/high_pass_filter.py
audiomentations/augmentations/high_shelf_filter.py
audiomentations/augmentations/lambda_transform.py
audiomentations/augmentations/limiter.py
audiomentations/augmentations/loudness_normalization.py
audiomentations/augmentations/low_pass_filter.py
audiomentations/augmentations/low_shelf_filter.py
audiomentations/augmentations/mp3_compression.py
audiomentations/augmentations/normalize.py
audiomentations/augmentations/padding.py
audiomentations/augmentations/peaking_filter.py
audiomentations/augmentations/pitch_shift.py
audiomentations/augmentations/polarity_inversion.py
audiomentations/augmentations/repeat_part.py
audiomentations/augmentations/resample.py
audiomentations/augmentations/reverse.py
audiomentations/augmentations/room_simulator.py
audiomentations/augmentations/seven_band_parametric_eq.py
audiomentations/augmentations/shift.py
audiomentations/augmentations/tanh_distortion.py
audiomentations/augmentations/time_mask.py
audiomentations/augmentations/time_stretch.py
audiomentations/augmentations/trim.py
audiomentations-0.43.1.dist-info/LICENSE
audiomentations-0.43.1.dist-info/METADATA
audiomentations-0.43.1.dist-info/WHEEL
audiomentations-0.43.1.dist-info/top_level.txt
audiomentations-0.43.1.dist-info/RECORD
