Metadata-Version: 2.1
Name: audiomentations
Version: 0.43.1
Summary: A Python library for audio data augmentation. Inspired by albumentations. Useful for machine learning.
Home-page: https://github.com/iver56/audiomentations
Author: Iver Jordal
License: MIT
Project-URL: Homepage, https://github.com/iver56/audiomentations
Project-URL: Documentation, https://iver56.github.io/audiomentations/
Project-URL: Changelog, https://iver56.github.io/audiomentations/changelog/
Project-URL: Issue Tracker, https://github.com/iver56/audiomentations/issues
Classifier: Programming Language :: Python :: 3.10
Classifier: Programming Language :: Python :: 3.11
Classifier: Programming Language :: Python :: 3.12
Classifier: Programming Language :: Python :: 3.13
Classifier: Operating System :: OS Independent
Classifier: Development Status :: 3 - Alpha
Classifier: Intended Audience :: Developers
Classifier: Intended Audience :: Science/Research
Classifier: Topic :: Multimedia
Classifier: Topic :: Multimedia :: Sound/Audio
Classifier: Topic :: Scientific/Engineering
Classifier: Topic :: Scientific/Engineering :: Artificial Intelligence
Requires-Python: >=3.10
License-File: LICENSE
Requires-Dist: numpy <3,>=1.22.0
Requires-Dist: numpy-minmax <1,>=0.3.0
Requires-Dist: numpy-rms <1,>=0.4.2
Requires-Dist: librosa !=0.10.0,<0.12.0,>=0.8.0
Requires-Dist: python-stretch <1,>=0.3.1
Requires-Dist: scipy <2,>=1.4
Requires-Dist: soxr <1.0.0,>=0.3.2
Provides-Extra: extras
Requires-Dist: fast-mp3-augment <1 ; extra == 'extras'
Requires-Dist: loudness <1 ; extra == 'extras'
Requires-Dist: numpy-audio-limiter <1 ; extra == 'extras'
Requires-Dist: pyroomacoustics >=0.7.4 ; extra == 'extras'
